design.v
module sequencedetector_1101 (
  input logic clk,
  input logic rst,
  input logic in,
  output logic out
);
  parameter s0 = 2'b00,
  			s1 = 2'b01,
  			s2 = 2'b10,
  			s3 = 2'b11;
  logic [1:0] state, next_state;
  
  always_ff @(posedge clk or posedge rst) begin
    if (rst)
      state <= s0;
    else
      state <= next_state;
  end
  
  always_comb begin
    case(state)
      s0:begin
        if (in)
          next_state = s1;
        else
          next_state = s0;
      end
      s1:begin
        if (in)
          next_state = s2;
        else
          next_state = s0;
      end
      s2:begin
        if (in)
          next_state = s2;
        else
          next_state = s3;
      end
      s3:begin
        if(in)
          next_state = s1;
        else
          next_state = s0;
      end
      
      
      default: next_state = s0;
      
    endcase
  end
      
  always_comb begin
    out = 1'b0;
    case(state)
      s3:begin
        if(in)
          out = 1'b1;
      end
    endcase
  end
endmodule

testbench.v
`timescale 1ns/1ps

module tb_sequencedetector_1101;
  reg clk;
  reg rst;
  reg in;
  wire out;

  sequencedetector_1101 dut (
    .clk(clk),
    .rst(rst),
    .in(in),
    .out(out)
  );

  always begin
    #5 clk = ~clk;
  end

  task send_bit(input logic bit_val);
    begin
      @(posedge clk);
      #1;
      in = bit_val;
    end
  endtask

  initial begin
    clk = 0;
    rst = 1;
    in = 0;

    repeat (2) @(posedge clk);
    #1 rst = 0;
    $display("Reset Released. Starting Tests");

    $display("Testing Non-matching sequence: 101010");
    send_bit(1);
    send_bit(0);
    send_bit(1);
    send_bit(0);
    send_bit(1);
    send_bit(0);
    
    @(posedge clk);
    #1;
    if (out !== 0) $error("ERROR: False detection during non-matching sequence!");
    $display("Testing standard sequence: 1101");
    send_bit(1);
    send_bit(1);
    send_bit(0);
    send_bit(1); 
    #2;
    if (out === 1'b1) begin
      $display("SUCCESS: '1101' detected successfully!");
    end else begin
      $error("ERROR: Failed to detect '1101'!");
    end

    $display("Testing overlapping sequence: 1101101");
    send_bit(1);
    send_bit(0);
    send_bit(1);
    if (out === 1'b1) begin
      $display("SUCCESS: Overlapping sequence '1101101' detected successfully!");
    end else begin
      $error("ERROR: Failed to detect overlapping sequence!");
    end

    repeat (5) @(posedge clk);
    $display("Testbench Completed");
    $finish;
  end

  initial begin
    $monitor("Time=%0t | rst=%b | in=%b | State=%b | out=%b", $time, rst, in, dut.state, out);
    
    $dumpfile("dump.vcd");
    $dumpvars;
  end

endmodule

dump.vcd
$date
	Sat Jul 25 02:15:58 2026
$end
$version
	Icarus Verilog
$end
$timescale
	1ps
$end
$scope module tb_sequencedetector_1101 $end
$var wire 1 ! out $end
$var reg 1 " clk $end
$var reg 1 # in $end
$var reg 1 $ rst $end
$scope module dut $end
$var wire 1 % clk $end
$var wire 1 & in $end
$var wire 1 ' rst $end
$var parameter 2 ( s0 $end
$var parameter 2 ) s1 $end
$var parameter 2 * s2 $end
$var parameter 2 + s3 $end
$var reg 2 , next_state [1:0] $end
$var reg 1 - out $end
$var reg 2 . state [1:0] $end
$upscope $end
$scope task send_bit $end
$var reg 1 / bit_val $end
$upscope $end
$upscope $end
$enddefinitions $end
$comment Show the parameter values. $end
$dumpall
b11 +
b10 *
b1 )
b0 (
$end
#0
$dumpvars
x/
b0 .
0-
b0 ,
1'
0&
0%
1$
0#
0"
0!
$end
#5000
1%
1"
#10000
0%
0"
#15000
1%
1"
#16000
1/
0'
0$
#20000
0%
0"
#25000
1%
1"
#26000
b1 ,
0/
1&
1#
#30000
0%
0"
#35000
b10 ,
b1 .
1%
1"
#36000
b0 ,
1/
0&
0#
#40000
0%
0"
#45000
b0 .
1%
1"
#46000
b1 ,
0/
1&
1#
#50000
0%
0"
#55000
b10 ,
b1 .
1%
1"
#56000
b0 ,
1/
0&
0#
#60000
0%
0"
#65000
b0 .
1%
1"
#66000
b1 ,
0/
1&
1#
#70000
0%
0"
#75000
b10 ,
b1 .
1%
1"
#76000
b0 ,
0&
0#
#80000
0%
0"
#85000
b0 .
1%
1"
#86000
1/
#90000
0%
0"
#95000
1%
1"
#96000
b1 ,
1&
1#
#100000
0%
0"
#105000
b10 ,
b1 .
1%
1"
#106000
0/
#110000
0%
0"
#115000
b10 .
1%
1"
#116000
b11 ,
1/
0&
0#
#120000
0%
0"
#125000
b0 ,
b11 .
1%
1"
#126000
b1 ,
1!
1-
1&
1#
#130000
0%
0"
#135000
b10 ,
0!
0-
b1 .
1%
1"
#136000
0/
#140000
0%
0"
#145000
b10 .
1%
1"
#146000
b11 ,
1/
0&
0#
#150000
0%
0"
#155000
b0 ,
b11 .
1%
1"
#156000
b1 ,
1!
1-
1&
1#
#160000
0%
0"
#165000
b10 ,
0!
0-
b1 .
1%
1"
#170000
0%
0"
#175000
b10 .
1%
1"
